README.md
pyproject.toml
setup.cfg
setup.py
django_gcp_iap_auth/apps.py
django_gcp_iap_auth/middleware.py
django_gcp_iap_auth/urls.py
django_gcp_iap_auth/views.py
django_gcp_iap_auth.egg-info/PKG-INFO
django_gcp_iap_auth.egg-info/SOURCES.txt
django_gcp_iap_auth.egg-info/dependency_links.txt
django_gcp_iap_auth.egg-info/requires.txt
django_gcp_iap_auth.egg-info/top_level.txt